payla_utils/__init__.py
payla_utils/apps.py
payla_utils/kafka.py
payla_utils/settings.py
payla_utils/access/README.md
payla_utils/access/__init__.py
payla_utils/access/decorators.py
payla_utils/access/permission.py
payla_utils/celery/__init__.py
payla_utils/logging/__init__.py
payla_utils/logging/default_configuration.py
payla_utils/logging/logformatter.py
payla_utils/logging/logger.py
payla_utils/logging/middlewares.py
payla_utils/logging/sentry_logger.py
payla_utils/management/__init__.py
payla_utils/management/commands/__init__.py
payla_utils/management/commands/gitlab_sql_migration.py
payla_utils/management/commands/i18n.py
payla_utils/management/commands/init_environment.py
payla_utils/management/commands/register_schemas.py
payla_utils/management/commands/sync_groups.py
payla_utils/models/__init__.py
payla_utils/models/base.py
payla_utils/oidc/__init__.py
payla_utils/oidc/backends.py
payla_utils/oidc/context_processors.py
payla_utils/scripts/__init__.py
payla_utils/scripts/custom_test_script.py
payla_utils/streaming/__init__.py
payla_utils/streaming/topics.py
payla_utils/templates/admin/login.html
payla_utils-0.3.24.dist-info/METADATA
payla_utils-0.3.24.dist-info/WHEEL
payla_utils-0.3.24.dist-info/RECORD
