Metadata-Version: 2.4
Name: payla-utils
Version: 0.3.24
Summary: payla_utils python package
Author-email: Payla Services <tools@payla.de>
Keywords: payla_utils
Classifier: Development Status :: 2 - Pre-Alpha
Classifier: Intended Audience :: Developers
Classifier: Natural Language :: English
Classifier: Programming Language :: Python :: 3
Classifier: Programming Language :: Python :: 3.11
Classifier: Programming Language :: Python :: 3.12
Classifier: Programming Language :: Python :: 3.13
Requires-Python: <4,>=3.11
Requires-Dist: django-admin-interface==0.31.*
Requires-Dist: django-extensions>=3.2.1
Requires-Dist: django-ipware>=6.0
Requires-Dist: django-pgtrigger>=4.7.0
Requires-Dist: django>=4.0
Requires-Dist: djangorestframework>=3.14.0
Requires-Dist: httpx>=0.28.1
Requires-Dist: pydantic>=2.10.3
Requires-Dist: python-json-logger==4.*
Requires-Dist: pyyaml>=6.0
Requires-Dist: sentry-sdk>=1.0
Requires-Dist: structlog-sentry==2.*
Requires-Dist: structlog==25.*
Provides-Extra: history
Requires-Dist: django-simple-history<4,>=3.4.0; extra == 'history'
Provides-Extra: oidc
Requires-Dist: mozilla-django-oidc>=4.0.1; extra == 'oidc'
Provides-Extra: streaming
Requires-Dist: confluent-kafka[avro]==2.12.1; extra == 'streaming'
Requires-Dist: fastavro==1.12.0; extra == 'streaming'
